visyn_core/.gitignore
visyn_core/__init__.py
visyn_core/__main__.py
visyn_core/dbmanager.py
visyn_core/dbview.py
visyn_core/dev_app.py
visyn_core/dev_celery.py
visyn_core/manager.py
visyn_core/utils.py
visyn_core/xlsx.py
visyn_core/celery/app.py
visyn_core/celery/main.py
visyn_core/cmd/__init__.py
visyn_core/cmd/__main__.py
visyn_core/dbmigration/__init__.py
visyn_core/dbmigration/dbmigration.ini
visyn_core/dbmigration/env.py
visyn_core/dbmigration/manager.py
visyn_core/id_mapping/__init__.py
visyn_core/id_mapping/idtype_api.py
visyn_core/id_mapping/manager.py
visyn_core/middleware/__init__.py
visyn_core/middleware/close_web_sessions_middleware.py
visyn_core/middleware/exception_handler_middleware.py
visyn_core/middleware/fastapi_metrics_middleware.py
visyn_core/middleware/request_context_plugin.py
visyn_core/plugin/__init__.py
visyn_core/plugin/model.py
visyn_core/plugin/parser.py
visyn_core/plugin/registry.py
visyn_core/plugin/router.py
visyn_core/rdkit/img_api.py
visyn_core/rdkit/models.py
visyn_core/rdkit/util/__init__.py
visyn_core/rdkit/util/draw.py
visyn_core/rdkit/util/molecule.py
visyn_core/security/__init__.py
visyn_core/security/dependencies.py
visyn_core/security/jwt_router.py
visyn_core/security/manager.py
visyn_core/security/model.py
visyn_core/security/permissions.py
visyn_core/security/store/__init__.py
visyn_core/security/store/alb_security_store.py
visyn_core/security/store/base_store.py
visyn_core/security/store/dummy_store.py
visyn_core/security/store/no_security_store.py
visyn_core/security/store/oauth2_security_store.py
visyn_core/security/utils/__init__.py
visyn_core/security/utils/encryptor.py
visyn_core/sentry/__init__.py
visyn_core/sentry/sentry_integration.py
visyn_core/sentry/sentry_proxy_router.py
visyn_core/server/__init__.py
visyn_core/server/cmd.py
visyn_core/server/main.py
visyn_core/server/mainapp.py
visyn_core/server/utils.py
visyn_core/server/visyn_server.py
visyn_core/server/public/500.html
visyn_core/server/public/favicon.png
visyn_core-17.10.0.dist-info/licenses/LICENSE
visyn_core-17.10.0.dist-info/METADATA
visyn_core-17.10.0.dist-info/WHEEL
visyn_core-17.10.0.dist-info/entry_points.txt
visyn_core-17.10.0.dist-info/top_level.txt
visyn_core-17.10.0.dist-info/RECORD
